[
  {
    "response": "It was cold alright \ud83d\ude29I had to protect my nutsack",
    "previous": [
      "WHY HE GRABBIN HIS NUTS\u2049\ufe0f\u2049\ufe0f\ud83d\ude29\ud83d\udca6",
      "'a-haaaaaa'",
      "WHY R U PULLING SUCH A FUCKBOY FACE DAVID HAHAAHAH"
    ]
  },
  {
    "response": "<:pog:718472362168942663>",
    "previous": [
      "Daddy and Kitten \ud83d\ude29\ud83d\ude33\ud83d\udca6",
      "<:despair:717734846872420382>",
      "same energy"
    ]
  },
  {
    "response": "One of my greatest pieces of photography",
    "previous": ["Thank you \ud83d\ude4f", "such an aesthetic photo", "LMFAO"]
  },
  {
    "response": "Thank you \ud83d\ude4f",
    "previous": ["such an aesthetic photo", "LMFAO", "BRO IS STRRESSSEDDDD"]
  },
  {
    "response": "No Boris it\u2019s coke",
    "previous": [
      "is this man snorting vitamin c",
      "snort it lmao",
      "the ones that dissolve in water??"
    ]
  },
  {
    "response": "Crushed up vitamin C pills actually !!!!??",
    "previous": [
      "david on that sawdust",
      "New generation maths revision tried and tested",
      ""
    ]
  },
  {
    "response": "New generation maths revision tried and tested",
    "previous": [
      "",
      "https://tenor.com/view/the-rock-dwayne-johnson-bend-gif-9667013",
      "Who needs revision when you have this"
    ]
  },
  {
    "response": "",
    "previous": [
      "https://tenor.com/view/the-rock-dwayne-johnson-bend-gif-9667013",
      "Who needs revision when you have this",
      "https://tenor.com/view/nervous-sign-of-the-cross-praying-hoping-nico-santos-gif-10946409"
    ]
  },
  {
    "response": "Who needs revision when you have this",
    "previous": [
      "https://tenor.com/view/nervous-sign-of-the-cross-praying-hoping-nico-santos-gif-10946409",
      "Oh",
      "cosine rule?"
    ]
  },
  {
    "response": "wouldnt it just be +-",
    "previous": [
      "Ok heah",
      "Yeah how do you use the cast diagram?",
      "you know that cos is negative with angles between 90* and 180*"
    ]
  }
]
